psicalc/__init__.py
psicalc/nmi.py
psicalc/nmi_util.py
psicalc/psicalc.py
psicalc-0.6.3.dist-info/METADATA
psicalc-0.6.3.dist-info/WHEEL
psicalc-0.6.3.dist-info/RECORD
