Metadata-Version: 2.3
Name: psicalc
Version: 0.6.3
Summary: Algorithm for clustering protein multiple sequence alignments using normalized mutual information.
Project-URL: Homepage, https://github.com/jdeweeselab/psicalc-package
Author-email: Joe Deweese Lab <jdeweeselab@gmail.com>, Thomas Townsley <thomas@mandosoft.dev>, Marc Soda <4rqh5y4p@duck.com>
Keywords: bioinformatics
Classifier: License :: OSI Approved :: MIT License
Classifier: Operating System :: OS Independent
Classifier: Programming Language :: Python :: 3
Requires-Python: >=3.6
Requires-Dist: numpy
Requires-Dist: pandas
Requires-Dist: scikit-learn
Requires-Dist: scipy
